quark_plugin_bp/__init__.py
quark_plugin_bp/bp_mip_mapping.py
quark_plugin_bp/bp_problem_provider.py
quark_plugin_bp/bp_qubo_mapping.py
quark_plugin_bp/utils.py
quark_plugin_bp-0.1.2.dist-info/licenses/LICENSE
quark_plugin_bp-0.1.2.dist-info/licenses/NOTICE
quark_plugin_bp-0.1.2.dist-info/METADATA
quark_plugin_bp-0.1.2.dist-info/WHEEL
quark_plugin_bp-0.1.2.dist-info/top_level.txt
quark_plugin_bp-0.1.2.dist-info/RECORD
