Metadata-Version: 2.4
Name: QUARK-plugin-bp
Version: 0.1.2
Author-email: Philipp Ross <philipp.ross@bmw.de>, Marvin Erdmann <marvin.erdmann@bmw.de>, Andre Luckow <andre.luckow@bmwgroup.com>, Greshma Shaji <greshma.shaji@bmwgroup.com>, Florian Kiwit <florian.kiwit@bmw.de>, Benjamin Decker <benjamin.decker@bmw.de>
License-Expression: Apache-2.0
Project-URL: Homepage, https://github.com/QUARK-framework/QUARK-plugin-bp
Classifier: Programming Language :: Python :: 3
Classifier: Operating System :: OS Independent
Requires-Python: >=3.12
License-File: LICENSE
License-File: NOTICE
Requires-Dist: docplex>=2.29.245
Requires-Dist: numpy>=2.3.1
Requires-Dist: pyscipopt>=5.5.0
Requires-Dist: qiskit-optimization>=0.6.1
Requires-Dist: quark-framework>=0.3.7
Dynamic: license-file
